statscache
statscache/plugins
