Metadata-Version: 1.1
Name: statscache
Version: 0.0.4
Summary: Daemon to build and keep fedmsg statistics
Home-page: https://github.com/fedora-infra/statscache/
Author: Ralph Bean
Author-email: rbean@redhat.com
License: LGPLv2+
Download-URL: https://pypi.python.org/pypi/statscache/
Platform: UNKNOWN
Classifier: Environment :: Web Environment
Classifier: Topic :: Software Development :: Libraries :: Python Modules
Classifier: Intended Audience :: Developers
Classifier: Programming Language :: Python
